jokoor/__init__.py
jokoor/client.py
jokoor/errors.py
jokoor/http_client.py
jokoor/result.py
jokoor/types.py
jokoor/resources/__init__.py
jokoor/resources/bank_accounts.py
jokoor/resources/campaigns.py
jokoor/resources/checkouts.py
jokoor/resources/contact_groups.py
jokoor/resources/contacts.py
jokoor/resources/customers.py
jokoor/resources/donations.py
jokoor/resources/invoices.py
jokoor/resources/payment_links.py
jokoor/resources/payments.py
jokoor/resources/payouts.py
jokoor/resources/products.py
jokoor/resources/receipts.py
jokoor/resources/recipients.py
jokoor/resources/refunds.py
jokoor/resources/sender_ids.py
jokoor/resources/sms.py
jokoor/resources/subscriptions.py
jokoor/resources/templates.py
jokoor/resources/transactions.py
jokoor/resources/webhook_events.py
jokoor/resources/webhooks.py
jokoor-2.0.0.dist-info/METADATA
jokoor-2.0.0.dist-info/WHEEL
jokoor-2.0.0.dist-info/top_level.txt
jokoor-2.0.0.dist-info/RECORD
