Metadata-Version: 2.4
Name: jokoor
Version: 2.0.0
Summary: Official Python SDK for the Jokoor API
Author-email: Jokoor <hello@jokoor.com>
Maintainer-email: Jokoor <hello@jokoor.com>
License-Expression: MIT
Project-URL: Homepage, https://jokoor.com
Project-URL: Documentation, https://docs.jokoor.com
Project-URL: Repository, https://github.com/jokoor/sdk-python
Project-URL: Issues, https://github.com/jokoor/sdk-python/issues
Keywords: jokoor,sms,payments,api,sdk,wave,gambia,africa
Classifier: Development Status :: 5 - Production/Stable
Classifier: Intended Audience :: Developers
Classifier: Operating System :: OS Independent
Classifier: Programming Language :: Python :: 3
Classifier: Programming Language :: Python :: 3.8
Classifier: Programming Language :: Python :: 3.9
Classifier: Programming Language :: Python :: 3.10
Classifier: Programming Language :: Python :: 3.11
Classifier: Programming Language :: Python :: 3.12
Classifier: Programming Language :: Python :: 3.13
Classifier: Topic :: Software Development :: Libraries :: Python Modules
Classifier: Topic :: Communications
Classifier: Topic :: Office/Business :: Financial :: Point-Of-Sale
Requires-Python: >=3.8
Requires-Dist: requests>=2.28.0
Requires-Dist: urllib3>=1.26.0
Provides-Extra: dev
Requires-Dist: pytest>=7.0.0; extra == "dev"
Requires-Dist: pytest-cov>=4.0.0; extra == "dev"
Requires-Dist: pytest-mock>=3.10.0; extra == "dev"
Requires-Dist: responses>=0.22.0; extra == "dev"
Requires-Dist: black>=23.0.0; extra == "dev"
Requires-Dist: mypy>=1.0.0; extra == "dev"
Requires-Dist: flake8>=6.0.0; extra == "dev"
Requires-Dist: types-requests>=2.28.0; extra == "dev"
